rds/__init__.py
rds/catalog.py
rds/dataproduct.py
rds/server.py
rds/utility.py
tests/__init__.py
tests/test_rds.py
mtna_rds-0.2.18.dist-info/LICENSE
mtna_rds-0.2.18.dist-info/METADATA
mtna_rds-0.2.18.dist-info/WHEEL
mtna_rds-0.2.18.dist-info/top_level.txt
mtna_rds-0.2.18.dist-info/RECORD
