Metadata-Version: 2.1
Name: mtna-rds
Version: 0.2.18
Summary: A library to query the Rich Data Services API framework developed by MTNA
Home-page: https://github.com/mtna/rds-python/
Author: Metadata Technology North America Inc.
Author-email: mtna@mtna.us
License: UNKNOWN
Platform: UNKNOWN
Classifier: Topic :: Database :: Database Engines/Servers
Classifier: Natural Language :: English
Classifier: Development Status :: 3 - Alpha
Classifier: Programming Language :: Python :: 2.7
Classifier: Programming Language :: Python :: 3.6
Classifier: Programming Language :: Python :: 3.7
Classifier: Programming Language :: Python :: 3.8
Classifier: License :: OSI Approved :: Apache Software License
Classifier: Operating System :: OS Independent
Requires-Python: >=2.7, !=3.0.*, !=3.1.*, !=3.2.*, !=3.3.*, !=3.4.*, !=3.5.*, <4
